gkjh/__init__.py
gkjh/expr_formatting.py
gkjh/misc.py
gkjh/lambdas/__init__.py
gkjh/lambdas/chaining.py
gkjh/lambdas/subs.py
gkjh-0.1.0.dist-info/LICENSE
gkjh-0.1.0.dist-info/METADATA
gkjh-0.1.0.dist-info/WHEEL
gkjh-0.1.0.dist-info/top_level.txt
gkjh-0.1.0.dist-info/RECORD
