Metadata-Version: 2.1
Name: gkjh
Version: 0.1.0
Summary: Gary Kim Jupyter Helpers
Author-email: Gary Kim <gary@garykim.dev>
License: GNU AFFERO GENERAL PUBLIC LICENSE
Project-URL: Homepage, https://sr.ht/~gary-kim/gkjh
Project-URL: Repository, https://git.sr.ht/~gary-kim/gkjh
Requires-Python: >=3.8
License-File: LICENSE
Requires-Dist: sympy ==1.12
Requires-Dist: matplotlib >=3.8
Requires-Dist: pandas >=1.5
Provides-Extra: dev
Requires-Dist: black ; extra == 'dev'
Requires-Dist: pytest ; extra == 'dev'
Provides-Extra: extras
Requires-Dist: pandas-datareader >=0.10.0 ; extra == 'extras'
Requires-Dist: yfinance >=0.2.36 ; extra == 'extras'
Requires-Dist: control >=0.9.4 ; extra == 'extras'
